{
  "kind": "singleType",
  "collectionName": "hero_contents",
  "info": {
    "singularName": "hero-content",
    "pluralName": "hero-contents",
    "displayName": "heroContent"
  },
  "options": {
    "draftAndPublish": true
  },
  "pluginOptions": {},
  "attributes": {
    "heroImageArray": {
      "type": "media",
      "multiple": true,
      "required": true,
      "allowedTypes": [
        "images"
      ]
    },
    "heroTitleFirstLine": {
      "type": "string",
      "required": true
    },
    "heroTitleSecondLine": {
      "type": "string"
    },
    "heroDescription": {
      "type": "text",
      "required": true
    }
  }
}
